[{
    "popenumber": 1, 
    "birthname": "Shimon Bar Yonah",
    "papalname": "Peter",
    "birthyear": 1,
    "deathyear": 68,
    "reignbegin":30,
    "reignend": 68
},
{
    "popenumber": 2, 
    "birthname": "Linus",
    "papalname": "Linus",
    "birthyear": 10,
    "deathyear": 76,
    "reignbegin":68,
    "reignend": 76
},
{
    "popenumber": 3, 
    "birthname": "Anacletus",
    "papalname": "Anacletus",
    "birthyear": 25,
    "deathyear": 92,
    "reignbegin":76,
    "reignend": 92
}]